LICENSE
README.md
mlpp_lib/__init__.py
mlpp_lib/callbacks.py
mlpp_lib/datasets.py
mlpp_lib/decorators.py
mlpp_lib/ensemble.py
mlpp_lib/losses.py
mlpp_lib/metrics.py
mlpp_lib/model_selection.py
mlpp_lib/models.py
mlpp_lib/normalizers.py
mlpp_lib/physical_layers.py
mlpp_lib/probabilistic_layers.py
mlpp_lib/standardizers.py
mlpp_lib/train.py
mlpp_lib/utils.py
mlpp_lib-0.14.0.dist-info/LICENSE
mlpp_lib-0.14.0.dist-info/METADATA
mlpp_lib-0.14.0.dist-info/WHEEL
mlpp_lib-0.14.0.dist-info/RECORD
